mpl_gradients/__init__.py
mpl_gradients-0.2.1.dist-info/licenses/LICENSE.txt
mpl_gradients-0.2.1.dist-info/METADATA
mpl_gradients-0.2.1.dist-info/WHEEL
mpl_gradients-0.2.1.dist-info/top_level.txt
mpl_gradients-0.2.1.dist-info/RECORD
