Metadata-Version: 2.4
Name: mpl-gradients
Version: 0.2.1
Summary: Gradient fills for Matplotlib charts using Agg filters
Author-email: Sanrishi <sharmasanchitrishi@mail.com>
License-Expression: MIT
Project-URL: Homepage, https://github.com/sanrishi/mpl-gradients
Requires-Python: >=3.9
License-File: LICENSE.txt
Requires-Dist: matplotlib
Requires-Dist: numpy
Dynamic: license-file
